[
{
  "fields": {
    "nombre": "Departamento 1",
    "precio_fuera_de_temporada": "2400",
    "capacidad": 5
  },
  "model": "lacalma.departamento",
  "pk": 1
},
{
  "fields": {
    "nombre": "Departamento 4",
    "precio_fuera_de_temporada": "2400",
    "capacidad": 5
  },
  "model": "lacalma.departamento",
  "pk": 2
},
{
  "fields": {
    "nombre": "Departamento 2",
    "precio_fuera_de_temporada": "2000",
    "capacidad": 4
  },
  "model": "lacalma.departamento",
  "pk": 3
},
{
  "fields": {
    "nombre": "Departamento 3",
    "precio_fuera_de_temporada": "2000",
    "capacidad": 4
  },
  "model": "lacalma.departamento",
  "pk": 4
}
]